transmutate/Services.py
transmutate/__init__.py
transmutate/base_model.py
transmutate/json_handler.py
transmutate/jsonb_handler.py
transmutate/proto_generator.py
transmutate/proto_handler.py
transmutate-0.2.2.dist-info/LICENSE
transmutate-0.2.2.dist-info/METADATA
transmutate-0.2.2.dist-info/WHEEL
transmutate-0.2.2.dist-info/RECORD
