Metadata-Version: 2.1
Name: transmutate
Version: 0.2.2
Summary: A versatile library for transforming and serializing data models into multiple formats.
License: MIT
Author: Ali Tavallaie
Author-email: a.tavallaie@gmail.com
Requires-Python: >=3.8,<4.0
Classifier: License :: OSI Approved :: MIT License
Classifier: Programming Language :: Python :: 3
Classifier: Programming Language :: Python :: 3.8
Classifier: Programming Language :: Python :: 3.9
Classifier: Programming Language :: Python :: 3.10
Classifier: Programming Language :: Python :: 3.11
Classifier: Programming Language :: Python :: 3.12
